{
  "name": "FamilyHostingMain",
  "displayName": "",
  "links": [
    {
      "name": "SafePlace",
      "displayName": "מקום בטוח - Safe Place",
      "shortDescription": "יוזמה לאיתור מארחים נדיבים בארץ",
      "description": "היוזמה מאפשרת למצוא מארחים נדיבים...",
      "url": "https://safe-zone.spiritt.app/",
      "website": "https://safe-zone.spiritt.app/"
    },
    {
      "name": "AtarMearhim",
      "displayName": "אתר מארחים",
      "shortDescription": "חיפוש בתים מארחים למשפחות",
      "description": "אתר לחיפוש בתים מארחים למשפחות",
      "url": "https://mearhim.vercel.app",
      "website": "https://mearhim.vercel.app"
    },
    {
      "name": "MiklatMugan",
      "displayName": "מקלט מוגן",
      "shortDescription": "לוח מודעות לחיפוש בתים מארחים",
      "description": "לוח מודעות לחיפוש בתים מארחים",
      "url": "https://protected-shelter.vercel.app",
      "website": "https://protected-shelter.vercel.app"
    },
    {
      "name": "MitaBetooha",
      "displayName": "מיטה בטוחה - Safe Bed",
      "shortDescription": "אתר התנדבותי לאירוח בזמני עימות",
      "description": "האתר 'מיטה בטוחה' הוא אתר התנדבותי...",
      "url": "https://safe-bed.info",
      "email": "contact@ryware.dev",
      "tags": [
        "אירוח"
      ]
    },
    {
      "name": "PeopleFromSouthHosting",
      "displayName": "אירוח משפחות מהדרום",
      "shortDescription": "ואצאפ לחיבור בין מארחים למשפחות בדרום",
      "description": "קבוצת וואטסאפ לחיבור בין בתים מארחים למשפחות",
      "url": "https://chat.whatsapp.com/E6GofQiyosDLndYKKCcC4v",
      "whatsapp": "https://chat.whatsapp.com/E6GofQiyosDLndYKKCcC4v"
    },
    {
      "name": "AbraHosting",
      "displayName": "אברא - בית ישראל",
      "shortDescription": "אירוח לתקופת המלחמה במגוון בתים",
      "description": "הפלטפורמה מאפשרת חיבור והתאמה בין משפחות...",
      "url": "https://bait-israeli.abra-it.com/",
      "website": "https://bait-israeli.abra-it.com/"
    },
    {
      "name": "HostingFromTheHeart",
      "displayName": "אירוח מהלב",
      "shortDescription": "אפליקציה לאירוח בביטחה במלחמה",
      "description": "האפליקציה ״אירוח מהלב״ נועדה לחבר בין אנשים...",
      "url": "https://www.letitsorti.com/hostingfromtheheartapp",
      "website": "https://www.letitsorti.com/hostingfromtheheartapp"
    },
    {
      "name": "BrothersHostingBrothers",
      "displayName": "אחים מארחים אחים",
      "shortDescription": "תאום אירוח בין אנשים בתגובה למלחמה",
      "description": "מיזם המתאים בין אורחים למארחים...",
      "url": "https://apartments-brokerage.onrender.com/",
      "website": "https://apartments-brokerage.onrender.com/",
      "contactEmail": "apartmentbrokerage22@gmail.com",
      "tags": [
        "אירוח",
        "אחים",
        "דירה",
        "מלחמה",
        "תרומה",
        "קהילה"
      ]
    }
  ]
}
