{
  "name": "TransportationMain",
  "displayName": "כללי",
  "links": [
    {
      "name": "HamalFoodLogistics",
      "displayName": "חמ״ל שינוע מזון לחיילים",
      "shortDescription": "קבוצת וואטסאפ לתיאום ושינוע של מזון ללוחמים",
      "description": "קבוצת וואטסאפ לתיאום ושינוע של מזון ללוחמים",
      "url": "https://chat.whatsapp.com/KPZ7JqQyBLG3OSvtGlUAdx",
      "whatsapp": "https://chat.whatsapp.com/KPZ7JqQyBLG3OSvtGlUAdx"
    },
    {
      "name": "HamalDriversArtzi",
      "displayName": "חמל נהגים מתנדבים ארצי",
      "shortDescription": "חמל נהגים מתנדבים ארצי",
      "description": "חמל נהגים מתנדבים ארצי",
      "url": "https://sh.hagai.co/vdri/",
      "website": "https://sh.hagai.co/vdri/",
      "initiativeImage": "https://pps.whatsapp.net/v/t61.24694-24/328638286_308153971976294_7092506465584154056_n.jpg?ccb=11-4&oh=01_AdQ-R72aPI7a1e26bvJU0mwrGIaaiX1WuY4EH7cqKlDdvw&oe=654A5786&_nc_sid=000000&_nc_cat=101",
      "whatsapp": "https://chat.whatsapp.com/Hm77B53MNjfBhgjmMP0C2s"
    }
  ]
}